confidant_py/__init__.py
confidant_py/decryption.py
confidant_py/exceptions.py
confidant_py/loader.py
confidant_py-0.2.0.dist-info/METADATA
confidant_py-0.2.0.dist-info/WHEEL
confidant_py-0.2.0.dist-info/top_level.txt
confidant_py-0.2.0.dist-info/RECORD
