Metadata-Version: 2.1
Name: confidant-py
Version: 0.2.0
Summary: Multi platform scalable environment variables manager.
Home-page: https://github.com/mr-vaibh/confidant-py
Author: Vaibhav
Author-email: shuklavaibhav336@gmail.com
Classifier: Programming Language :: Python :: 3
Classifier: License :: OSI Approved :: MIT License
Classifier: Operating System :: OS Independent
Requires-Python: >=3.7
Requires-Dist: cryptography
